odoo10_addon_purchase_commercial_partner-10.0.1.0.0-py2.7-nspkg.pth
odoo/addons/purchase_commercial_partner/README.rst
odoo/addons/purchase_commercial_partner/__init__.py
odoo/addons/purchase_commercial_partner/__manifest__.py
odoo/addons/purchase_commercial_partner/i18n/de.po
odoo/addons/purchase_commercial_partner/i18n/es.po
odoo/addons/purchase_commercial_partner/i18n/fr.po
odoo/addons/purchase_commercial_partner/i18n/gl.po
odoo/addons/purchase_commercial_partner/i18n/it.po
odoo/addons/purchase_commercial_partner/i18n/nl.po
odoo/addons/purchase_commercial_partner/i18n/pt_BR.po
odoo/addons/purchase_commercial_partner/i18n/ro.po
odoo/addons/purchase_commercial_partner/i18n/sl.po
odoo/addons/purchase_commercial_partner/i18n/vi_VN.po
odoo/addons/purchase_commercial_partner/models/__init__.py
odoo/addons/purchase_commercial_partner/models/purchase.py
odoo/addons/purchase_commercial_partner/views/purchase.xml
odoo10_addon_purchase_commercial_partner-10.0.1.0.0.dist-info/DESCRIPTION.rst
odoo10_addon_purchase_commercial_partner-10.0.1.0.0.dist-info/METADATA
odoo10_addon_purchase_commercial_partner-10.0.1.0.0.dist-info/RECORD
odoo10_addon_purchase_commercial_partner-10.0.1.0.0.dist-info/WHEEL
odoo10_addon_purchase_commercial_partner-10.0.1.0.0.dist-info/metadata.json
odoo10_addon_purchase_commercial_partner-10.0.1.0.0.dist-info/namespace_packages.txt
odoo10_addon_purchase_commercial_partner-10.0.1.0.0.dist-info/top_level.txt
